LICENSE
bowline/__init__.py
bowline/preprocessors.py
bowline/py.typed
bowline/utils.py
bowline-0.2.2.dist-info/LICENSE
bowline-0.2.2.dist-info/WHEEL
bowline-0.2.2.dist-info/METADATA
bowline-0.2.2.dist-info/RECORD
